gguf_container/__init__.py
gguf_container/__main__.py
gguf_container/contract.sol
gguf_container/index.css
gguf_container/index.html
gguf_container/index.js
gguf_container/logo.png
gguf_container/server.py
gguf_container-0.0.7.dist-info/LICENSE
gguf_container-0.0.7.dist-info/WHEEL
gguf_container-0.0.7.dist-info/METADATA
gguf_container-0.0.7.dist-info/RECORD
