Metadata-Version: 2.1
Name: gguf-container
Version: 0.0.7
Summary: gguf-container (core + contract backend + local frontend)
Author-email: calcuis <info@calcu.io>
Classifier: License :: OSI Approved :: MIT License
Requires-Dist: gguf-core
Project-URL: Homepage, https://github.com/calcuis/container-frontend
Project-URL: Issues, https://github.com/calcuis/container-frontend/issues
